.coveragerc
.editorconfig
.gitattributes
.gitignore
.gitlab-ci.yml
.zenodo.json
AUTHORS.rst
CITATION
CONTRIBUTING.rst
HISTORY.rst
LICENSE
MANIFEST.in
Makefile
README.rst
setup.cfg
setup.py
tox.ini
.github/ISSUE_TEMPLATE.md
.github/create_release_from_gitlab_ci.sh
docs/Makefile
docs/about.rst
docs/api_cli_reference.rst
docs/conf.py
docs/contributing.rst
docs/credits.rst
docs/history.rst
docs/index.rst
docs/installation.rst
docs/make.bat
docs/usage.rst
docs/_build/html/_images/list_available_transformations_filtered.png
docs/_build/html/_images/list_available_transformations_no_filters.png
docs/_build/html/_static/file.png
docs/_build/html/_static/minus.png
docs/_build/html/_static/plus.png
docs/_static/custom.css
docs/images/list_available_transformations_filtered.png
docs/images/list_available_transformations_no_filters.png
docs/usage/available_transformations.rst
docs/usage/classifier_creation.rst
docs/usage/homogenization.rst
docs/usage/input_data_requirements.rst
spechomo/__init__.py
spechomo/classifier.py
spechomo/classifier_creation.py
spechomo/clustering.py
spechomo/exceptions.py
spechomo/logging.py
spechomo/options.py
spechomo/options_default.yaml
spechomo/prediction.py
spechomo/resampling.py
spechomo/training_data.py
spechomo/utils.py
spechomo/version.py
spechomo.egg-info/PKG-INFO
spechomo.egg-info/SOURCES.txt
spechomo.egg-info/dependency_links.txt
spechomo.egg-info/not-zip-safe
spechomo.egg-info/requires.txt
spechomo.egg-info/top_level.txt