Metadata-Version: 2.4
Name: spechomo
Version: 0.10.4
Summary: Spectral homogenization of multispectral satellite data.
Home-page: https://git.gfz-potsdam.de/geomultisens/spechomo
Author: Daniel Scheffler
Author-email: daniel.scheffler@gfz.de
License: Apache-2.0
Keywords: spechomo,spectral homogenization,sensor fusion,remote sensing
Classifier: Development Status :: 4 - Beta
Classifier: Intended Audience :: Developers
Classifier: License :: OSI Approved :: Apache Software License
Classifier: Natural Language :: English
Classifier: Programming Language :: Python :: 3
Classifier: Programming Language :: Python :: 3.6
Classifier: Programming Language :: Python :: 3.7
Classifier: Programming Language :: Python :: 3.8
Classifier: Programming Language :: Python :: 3.9
License-File: LICENSE
License-File: AUTHORS.rst
Requires-Dist: dill
Requires-Dist: geoarray>=0.15.0
Requires-Dist: matplotlib
Requires-Dist: natsort
Requires-Dist: nested_dict
Requires-Dist: numpy<2
Requires-Dist: pandas
Requires-Dist: pyrsr>=0.5.0
Requires-Dist: pyyaml
Requires-Dist: scikit-learn<1,>=0.23.2
Requires-Dist: scipy<1.11
Requires-Dist: seaborn
Requires-Dist: specclassify>=0.3.0
Requires-Dist: tabulate
Requires-Dist: tqdm
Provides-Extra: doc
Requires-Dist: sphinx-argparse; extra == "doc"
Requires-Dist: sphinx_rtd_theme; extra == "doc"
Requires-Dist: sphinx-autodoc-typehints; extra == "doc"
Provides-Extra: test
Requires-Dist: pytest; extra == "test"
Requires-Dist: pytest-cov; extra == "test"
Requires-Dist: pytest-reporter-html1; extra == "test"
Requires-Dist: urlchecker; extra == "test"
Provides-Extra: lint
Requires-Dist: flake8; extra == "lint"
Requires-Dist: pycodestyle; extra == "lint"
Requires-Dist: pydocstyle; extra == "lint"
Provides-Extra: dev
Requires-Dist: setuptools-git; extra == "dev"
Requires-Dist: pytest; extra == "dev"
Requires-Dist: pytest-cov; extra == "dev"
Requires-Dist: pytest-reporter-html1; extra == "dev"
Requires-Dist: urlchecker; extra == "dev"
Requires-Dist: sphinx-argparse; extra == "dev"
Requires-Dist: sphinx_rtd_theme; extra == "dev"
Requires-Dist: sphinx-autodoc-typehints; extra == "dev"
Requires-Dist: flake8; extra == "dev"
Requires-Dist: pycodestyle; extra == "dev"
Requires-Dist: pydocstyle; extra == "dev"
Dynamic: author
Dynamic: author-email
Dynamic: classifier
Dynamic: description
Dynamic: description-content-type
Dynamic: home-page
Dynamic: keywords
Dynamic: license
Dynamic: license-file
Dynamic: provides-extra
Dynamic: requires-dist
Dynamic: summary
